apinator/__init__.py
apinator/api.py
apinator/common.py
apinator/endpoint.py
apinator-0.1.1.dist-info/LICENSE
apinator-0.1.1.dist-info/WHEEL
apinator-0.1.1.dist-info/METADATA
apinator-0.1.1.dist-info/RECORD
