Metadata-Version: 2.1
Name: apinator
Version: 0.1.1
Summary: Library for building type-checked bindings to external REST APIs
Author-email: Rearc Data <data@rearc.io>
Requires-Python: >=3.7
Requires-Dist: typing_extensions>=4
Requires-Dist: pydantic>2
Requires-Dist: requests
Requires-Dist: sphinx ; extra == "dev"
Requires-Dist: sphinx-material ; extra == "dev"
Requires-Dist: sphinxcontrib-mermaid ; extra == "dev"
Requires-Dist: myst-parser ; extra == "dev"
Requires-Dist: pytest ; extra == "test"
Requires-Dist: pytest-cov ; extra == "test"
Requires-Dist: responses ; extra == "test"
Project-URL: Home, https://github.com/rearc-data/apinator
Provides-Extra: dev
Provides-Extra: test
